{
  "editor.tabSize": 2,
  "window.zoomLevel": 0,
  "workbench.colorTheme": "Solarized Light",
  "gitlens.advanced.messages": {
    "suppressCommitHasNoPreviousCommitWarning": false,
    "suppressCommitNotFoundWarning": false,
    "suppressFileNotUnderSourceControlWarning": false,
    "suppressGitVersionWarning": false,
    "suppressLineUncommittedWarning": false,
    "suppressNoRepositoryWarning": false,
    "suppressResultsExplorerNotice": false,
    "suppressShowKeyBindingsNotice": true,
    "suppressUpdateNotice": false,
    "suppressWelcomeNotice": true
  },
  "gitlens.keymap": "chorded",
  "prettier.singleQuote": true,
  "prettier.stylelintIntegration": true,
  "vim.leader": "รถ",
  "vim.handleKeys": {
    "<C-d>": true,
    "<C-w>": false,
    "<C-k>": false,
    "<C-b>": false,
    "<C-/>": false,
    "<C-*>": false,
    "<C-+>": false,
    "<C-f>": false,
    "<C-y>": false,
    "<C-J>": false
  },
  "vim.normalModeKeyBindingsNonRecursive": [
    {
      "before": ["leader", "d"],
      "after": [],
      "commands": [
        {
          "command": "editor.action.addSelectionToNextFindMatch",
          "args": []
        }
      ]
    },
    {
      "before": ["K"],
      "commands": [
        "workbench.action.nextEditor"
      ]
    },
    {
      "before": ["J"],
      "commands": [
        "workbench.action.previousEditor"
      ]
    }
  ],
  "gitlens.historyExplorer.enabled": true,
  "workbench.editor.enablePreviewFromQuickOpen": false,
  "breadcrumbs.enabled": true,
  "elm.makeCommand": "elm-make",
  "editor.formatOnSave": true,
  "codemetrics.basics.DecorationModeEnabled": false,
  "explorer.confirmDelete": false,
  "editor.renderWhitespace": "all",
  "typescript.updateImportsOnFileMove.enabled": "always"
}
